
<Lesson stage="3" page="7" type="Reading Check">
<APageParagraph activityIntroClip="uk/assets/sound/whiteSpace.mp3"  pencil="p3" skipIntro="true">
   <paragraph>
      <sentence>
         <text>The movies used to be in black and white with no sound.</text>
         <clip>uk/assets/sound/whiteSpace.mp3</clip>
      </sentence>
      <sentence>
         <text>Then in the 1920's there were considerable changes in how films were made.</text>
         <clip>uk/assets/sound/whiteSpace.mp3</clip>
      </sentence>
       <sentence>
         <text>CR</text>
         <clip></clip>
      </sentence>
      <sentence>
         <text>CR</text>
         <clip></clip>
      </sentence>       
      <sentence>
         <text>Once actors could talk on screen it changed their performances.</text>
         <clip>uk/assets/sound/whiteSpace.mp3</clip>
      </sentence>
      <sentence>
         <text>Soon sound and color in films were the norm.</text>
         <clip>uk/assets/sound/whiteSpace.mp3</clip>
      </sentence>
      <sentence>
         <text>As films became more popular, the film makers had a great deal of power.</text>
         <clip>uk/assets/sound/whiteSpace.mp3</clip>
      </sentence>
      <sentence>
         <text>They controlled the actors, the theaters and ticket sales.</text>
         <clip>uk/assets/sound/whiteSpace.mp3</clip>
      </sentence>
    </paragraph>
    <paragraph>
       <sentence>
         <text>CR</text>
         <clip></clip>
      </sentence>
      <sentence>
         <text>CR</text>
         <clip></clip>
      </sentence>       
      <sentence>
         <text>By 1939 there were more movie theaters in the US than there were banks.</text>
         <clip>uk/assets/sound/whiteSpace.mp3</clip>
      </sentence>
      <sentence>
         <text>Hollywood was the main center of film making in the world, not just in the USA.</text>
         <clip>uk/assets/sound/whiteSpace.mp3</clip>
      </sentence>
      <sentence>
         <text>The Golden Age of film ended when the Supreme Court ruled this control had to change.</text>
         <clip>uk/assets/sound/whiteSpace.mp3</clip>
	  </sentence>
	  <sentence>
		  <text>More changes came when TV found a place in all homes.</text>
		  <clip>uk/assets/sound/whiteSpace.mp3</clip>
	</sentence>
      <sentence>
         <text>Theaters were empty and the business went into decline.</text>
         <clip>uk/assets/sound/whiteSpace.mp3</clip>
      </sentence>
   </paragraph>
   <paragraph>
       <sentence>
         <text>CR</text>
         <clip></clip>
      </sentence>
      <sentence>
         <text>CR</text>
         <clip></clip>
      </sentence>   
      <sentence>
         <text>Yet, the medium of film did not die.</text>
         <clip>uk/assets/sound/whiteSpace.mp3</clip>
      </sentence>
       <sentence>
         <text>There were still people who liked to watch a film on a night out.</text>
         <clip>uk/assets/sound/whiteSpace.mp3</clip>
      </sentence>
      <sentence>
         <text>The movie business used new technology and changed the way films were made and shown.</text>
         <clip>uk/assets/sound/whiteSpace.mp3</clip>
	  </sentence>
      <sentence>
         <text>Wide screens and drive-ins were all part of the show.</text>
         <clip>uk/assets/sound/whiteSpace.mp3</clip>
	  </sentence>
	  <sentence>
		  <text>They made sure that they could give you something you couldn't get on TV.</text>
		  <clip>uk/assets/sound/whiteSpace.mp3</clip>
	  </sentence>
  </paragraph>
  <paragraph>
	  <sentence>
		  <text>CR</text>
		  <clip></clip>
	  </sentence>
	  <sentence>
		  <text>CR</text>
		  <clip></clip>
	  </sentence>
	  <sentence>
		  <text>Now, film makers use DVDs and gaming to do the same thing.</text>
		  <clip>uk/assets/sound/whiteSpace.mp3</clip>
	  </sentence>
	  <sentence>
		  <text>The movies are a big business and have come a long way from the orange groves of Hollywood.</text>
		  <clip>uk/assets/sound/whiteSpace.mp3</clip>
      </sentence>
  </paragraph>
</APageParagraph>
</Lesson>
